MANIFEST.in
pad_demo.xml
res_company.xml
setup.py
./__init__.py
./__openerp__.py
./pad.py
./res_company.py
./py_etherpad/__init__.py
i18n/ar.po
i18n/bg.po
i18n/ca.po
i18n/cs.po
i18n/da.po
i18n/de.po
i18n/es.po
i18n/es_CR.po
i18n/es_MX.po
i18n/es_VE.po
i18n/fi.po
i18n/fr.po
i18n/gl.po
i18n/hr.po
i18n/hu.po
i18n/it.po
i18n/ja.po
i18n/mk.po
i18n/mn.po
i18n/nb.po
i18n/nl.po
i18n/pad.pot
i18n/pl.po
i18n/pt.po
i18n/pt_BR.po
i18n/ro.po
i18n/ru.po
i18n/sl.po
i18n/sr@latin.po
i18n/sv.po
i18n/tr.po
i18n/zh_CN.po
openerp_pad.egg-info/PKG-INFO
openerp_pad.egg-info/SOURCES.txt
openerp_pad.egg-info/dependency_links.txt
openerp_pad.egg-info/requires.txt
openerp_pad.egg-info/top_level.txt
static/src/img/pad_link_companies.jpeg
static/src/js/pad.js
static/src/xml/pad.xml